seven_studio/__init__.py
seven_studio/route.py
seven_studio/handlers/__init__.py
seven_studio/handlers/studio_base.py
seven_studio/handlers/system/__init__.py
seven_studio/handlers/system/core.py
seven_studio/handlers/system/file.py
seven_studio/handlers/system/menu.py
seven_studio/handlers/system/power.py
seven_studio/handlers/system/product.py
seven_studio/handlers/system/settings.py
seven_studio/libs/__init__.py
seven_studio/libs/geetest.py
seven_studio/libs/file/__init__.py
seven_studio/libs/file/bos.py
seven_studio/libs/file/cos.py
seven_studio/libs/file/ks3.py
seven_studio/libs/file/oss2.py
seven_studio/libs/file/s3.py
seven_studio/libs/file/upload.py
seven_studio/models/__init__.py
seven_studio/models/dto_model.py
seven_studio/models/enum.py
seven_studio/models/power_model.py
seven_studio/models/seven_model.py
seven_studio/models/db_models/__init__.py
seven_studio/models/db_models/file/__init__.py
seven_studio/models/db_models/file/file_history_model.py
seven_studio/models/db_models/file/file_resource_model.py
seven_studio/models/db_models/file/file_restrict_model.py
seven_studio/models/db_models/file/file_restrict_pic_model.py
seven_studio/models/db_models/file/file_storage_path_model.py
seven_studio/models/db_models/file/file_water_image_model.py
seven_studio/models/db_models/log/__init__.py
seven_studio/models/db_models/log/log_action_model.py
seven_studio/models/db_models/menu/__init__.py
seven_studio/models/db_models/menu/menu_cote_model.py
seven_studio/models/db_models/menu/menu_info_model.py
seven_studio/models/db_models/menu/menu_info_model_ex.py
seven_studio/models/db_models/product/__init__.py
seven_studio/models/db_models/product/product_info_model.py
seven_studio/models/db_models/product/product_user_model.py
seven_studio/models/db_models/role/__init__.py
seven_studio/models/db_models/role/role_info_model.py
seven_studio/models/db_models/role/role_power_model.py
seven_studio/models/db_models/role/role_power_model_ex.py
seven_studio-1.6.10.dist-info/LICENSE
seven_studio-1.6.10.dist-info/METADATA
seven_studio-1.6.10.dist-info/WHEEL
seven_studio-1.6.10.dist-info/top_level.txt
seven_studio-1.6.10.dist-info/RECORD
